odoo10_addon_sale_order_invoicing_finished_task-10.0.1.0.3-py2.7-nspkg.pth
odoo/addons/sale_order_invoicing_finished_task/README.rst
odoo/addons/sale_order_invoicing_finished_task/__init__.py
odoo/addons/sale_order_invoicing_finished_task/__manifest__.py
odoo/addons/sale_order_invoicing_finished_task/i18n/ca.po
odoo/addons/sale_order_invoicing_finished_task/i18n/de.po
odoo/addons/sale_order_invoicing_finished_task/i18n/el_GR.po
odoo/addons/sale_order_invoicing_finished_task/i18n/es.po
odoo/addons/sale_order_invoicing_finished_task/i18n/es_ES.po
odoo/addons/sale_order_invoicing_finished_task/i18n/es_VE.po
odoo/addons/sale_order_invoicing_finished_task/i18n/fi.po
odoo/addons/sale_order_invoicing_finished_task/i18n/fr.po
odoo/addons/sale_order_invoicing_finished_task/i18n/hr.po
odoo/addons/sale_order_invoicing_finished_task/i18n/hr_HR.po
odoo/addons/sale_order_invoicing_finished_task/i18n/hu.po
odoo/addons/sale_order_invoicing_finished_task/i18n/it.po
odoo/addons/sale_order_invoicing_finished_task/i18n/nl.po
odoo/addons/sale_order_invoicing_finished_task/i18n/nl_NL.po
odoo/addons/sale_order_invoicing_finished_task/i18n/pt.po
odoo/addons/sale_order_invoicing_finished_task/i18n/pt_BR.po
odoo/addons/sale_order_invoicing_finished_task/i18n/ro.po
odoo/addons/sale_order_invoicing_finished_task/i18n/sk.po
odoo/addons/sale_order_invoicing_finished_task/i18n/sl.po
odoo/addons/sale_order_invoicing_finished_task/i18n/tr.po
odoo/addons/sale_order_invoicing_finished_task/i18n/tr_TR.po
odoo/addons/sale_order_invoicing_finished_task/i18n/vi_VN.po
odoo/addons/sale_order_invoicing_finished_task/i18n/zh_CN.po
odoo/addons/sale_order_invoicing_finished_task/models/__init__.py
odoo/addons/sale_order_invoicing_finished_task/models/product.py
odoo/addons/sale_order_invoicing_finished_task/models/project.py
odoo/addons/sale_order_invoicing_finished_task/models/sale_order.py
odoo/addons/sale_order_invoicing_finished_task/static/description/icon.png
odoo10_addon_sale_order_invoicing_finished_task-10.0.1.0.3.dist-info/DESCRIPTION.rst
odoo10_addon_sale_order_invoicing_finished_task-10.0.1.0.3.dist-info/METADATA
odoo10_addon_sale_order_invoicing_finished_task-10.0.1.0.3.dist-info/RECORD
odoo10_addon_sale_order_invoicing_finished_task-10.0.1.0.3.dist-info/WHEEL
odoo10_addon_sale_order_invoicing_finished_task-10.0.1.0.3.dist-info/metadata.json
odoo10_addon_sale_order_invoicing_finished_task-10.0.1.0.3.dist-info/namespace_packages.txt
odoo10_addon_sale_order_invoicing_finished_task-10.0.1.0.3.dist-info/top_level.txt
