Metadata-Version: 2.0
Name: odoo10-addon-sale-order-invoicing-finished-task
Version: 10.0.1.0.3
Summary: Control invoice order lines if his task has been finished
Home-page: https://github.com/OCA/sale-workflow
Author: Tecnativa, Camptocamp, Odoo Community Association (OCA)
Author-email: support@odoo-community.org
License: AGPL-3
Platform: UNKNOWN
Classifier: Programming Language :: Python
Classifier: Framework :: Odoo
Classifier: License :: OSI Approved :: GNU Affero General Public License v3
Requires-Python: ~=2.7
Requires-Dist: odoo (<10.1dev,>=10.0)
